[
  {
    "id": "8c234125-d2e6-40c6-a442-7e9e26dcb1c0",
    "user_profile_id": "56e8de59-76d8-496e-93fa-ec323c8285f6",
    "category": "home_purchase",
    "title": "Home Purchase",
    "target_amount": 2500000.0,
    "timeframe": "3-5 years",
    "current_amount": 0.0,
    "importance": "high",
    "flexibility": "fixed",
    "notes": "Saving for home purchase or down payment",
    "created_at": "2025-03-13T15:02:58.057813",
    "updated_at": "2025-03-13T15:04:06.440443",
    "current_progress": 0.0,
    "priority_score": 90.0,
    "additional_funding_sources": "",
    "goal_success_probability": 0.0,
    "adjustments_required": 0,
    "funding_strategy": "",
    "last_simulation_time": null,
    "simulation_data": null,
    "scenarios": null,
    "adjustments": null,
    "simulation_parameters_json": null
  },
  {
    "id": "a14f1025-7b17-4545-a13c-8d54da846d08",
    "user_profile_id": "56e8de59-76d8-496e-93fa-ec323c8285f6",
    "category": "traditional_retirement",
    "title": "Retirement at age 65",
    "target_amount": 20000000.0,
    "timeframe": "Age 65",
    "current_amount": 0.0,
    "importance": "high",
    "flexibility": "fixed",
    "notes": "Saving for retirement at age 65",
    "created_at": "2025-03-13T15:03:57.507062",
    "updated_at": "2025-03-13T15:04:06.443736",
    "current_progress": 0.0,
    "priority_score": 90.0,
    "additional_funding_sources": "",
    "goal_success_probability": 0.0,
    "adjustments_required": 0,
    "funding_strategy": "",
    "last_simulation_time": null,
    "simulation_data": null,
    "scenarios": null,
    "adjustments": null,
    "simulation_parameters_json": null
  },
  {
    "id": "9471d0e9-ee44-41e9-82d2-31c1639dc5d3",
    "user_profile_id": "3f63f29b-ae15-4909-aa31-ebb62092dfe4",
    "category": "home_purchase",
    "title": "Home Purchase",
    "target_amount": 15000000.0,
    "timeframe": "3-5 years",
    "current_amount": 0.0,
    "importance": "medium",
    "flexibility": "fixed",
    "notes": "Saving for home purchase or down payment",
    "created_at": "2025-03-14T22:54:35.239583",
    "updated_at": "2025-03-14T22:55:01.429903",
    "current_progress": 0.0,
    "priority_score": 70.0,
    "additional_funding_sources": "",
    "goal_success_probability": 0.0,
    "adjustments_required": 0,
    "funding_strategy": "",
    "last_simulation_time": null,
    "simulation_data": null,
    "scenarios": null,
    "adjustments": null,
    "simulation_parameters_json": null
  },
  {
    "id": "0a6a5bf7-6eb4-4fb2-b96a-0c85d2c5e1bb",
    "user_profile_id": "3f63f29b-ae15-4909-aa31-ebb62092dfe4",
    "category": "traditional_retirement",
    "title": "Retirement at age 65",
    "target_amount": 15000000.0,
    "timeframe": "Age 65",
    "current_amount": 0.0,
    "importance": "medium",
    "flexibility": "fixed",
    "notes": "Saving for retirement at age 65",
    "created_at": "2025-03-14T22:54:48.377387",
    "updated_at": "2025-03-14T22:55:01.434564",
    "current_progress": 0.0,
    "priority_score": 70.0,
    "additional_funding_sources": "",
    "goal_success_probability": 0.0,
    "adjustments_required": 0,
    "funding_strategy": "",
    "last_simulation_time": null,
    "simulation_data": null,
    "scenarios": null,
    "adjustments": null,
    "simulation_parameters_json": null
  },
  {
    "id": "ac0bda57-4218-4de8-aae5-b1da004b8d70",
    "user_profile_id": "050347bd-44da-456e-a17a-ed8ac38e7524",
    "category": "home_purchase",
    "title": "Home Purchase",
    "target_amount": 20000000.0,
    "timeframe": "3-5 years",
    "current_amount": 0.0,
    "importance": "high",
    "flexibility": "fixed",
    "notes": "Saving for home purchase or down payment",
    "created_at": "2025-03-15T14:14:42.021960",
    "updated_at": "2025-03-15T14:14:45.909924",
    "current_progress": 0.0,
    "priority_score": 90.0,
    "additional_funding_sources": "",
    "goal_success_probability": 0.0,
    "adjustments_required": 0,
    "funding_strategy": "",
    "last_simulation_time": null,
    "simulation_data": null,
    "scenarios": null,
    "adjustments": null,
    "simulation_parameters_json": null
  },
  {
    "id": "82ae83af-6aac-4d5f-9fca-323dff098315",
    "user_profile_id": "362c6853-fa35-4b90-adee-845284eec972",
    "category": "home_purchase",
    "title": "Home Purchase",
    "target_amount": 80000000.0,
    "timeframe": "5-10 years",
    "current_amount": 0.0,
    "importance": "medium",
    "flexibility": "fixed",
    "notes": "Saving for home purchase or down payment",
    "created_at": "2025-03-15T15:33:51.216463",
    "updated_at": "2025-03-15T15:33:54.271236",
    "current_progress": 0.0,
    "priority_score": 70.0,
    "additional_funding_sources": "",
    "goal_success_probability": 0.0,
    "adjustments_required": 0,
    "funding_strategy": "",
    "last_simulation_time": null,
    "simulation_data": null,
    "scenarios": null,
    "adjustments": null,
    "simulation_parameters_json": null
  },
  {
    "id": "082d5022-d6d9-4887-8add-f5d253a8b140",
    "user_profile_id": "8f2f1a99-3040-4351-8197-20fba4179ebe",
    "category": "home_purchase",
    "title": "Home Purchase",
    "target_amount": 90000000.0,
    "timeframe": "5-10 years",
    "current_amount": 0.0,
    "importance": "medium",
    "flexibility": "fixed",
    "notes": "Saving for home purchase or down payment",
    "created_at": "2025-03-15T17:06:24.093205",
    "updated_at": "2025-03-15T17:06:28.348942",
    "current_progress": 0.0,
    "priority_score": 70.0,
    "additional_funding_sources": "",
    "goal_success_probability": 0.0,
    "adjustments_required": 0,
    "funding_strategy": "",
    "last_simulation_time": null,
    "simulation_data": null,
    "scenarios": null,
    "adjustments": null,
    "simulation_parameters_json": null
  },
  {
    "id": "237b3b38-c60b-475c-96e5-ba769d5981af",
    "user_profile_id": "49104997-4a3d-4467-be09-fba5164a967a",
    "category": "home_purchase",
    "title": "Home Purchase",
    "target_amount": 10000000.0,
    "timeframe": "3-5 years",
    "current_amount": 0.0,
    "importance": "medium",
    "flexibility": "fixed",
    "notes": "Saving for home purchase or down payment",
    "created_at": "2025-03-16T08:27:20.071045",
    "updated_at": "2025-03-16T08:27:23.788644",
    "current_progress": 0.0,
    "priority_score": 70.0,
    "additional_funding_sources": "",
    "goal_success_probability": 0.0,
    "adjustments_required": 0,
    "funding_strategy": "",
    "last_simulation_time": null,
    "simulation_data": null,
    "scenarios": null,
    "adjustments": null,
    "simulation_parameters_json": null
  },
  {
    "id": "a273b8c6-dc5e-4e46-a317-a108c2cacbe6",
    "user_profile_id": "1b131cb6-fb0c-4131-98bb-86ad71ae0720",
    "category": "home_purchase",
    "title": "Home Purchase",
    "target_amount": 30000000.0,
    "timeframe": "3-5 years",
    "current_amount": 0.0,
    "importance": "medium",
    "flexibility": "fixed",
    "notes": "Saving for home purchase or down payment",
    "created_at": "2025-03-16T20:52:47.130325",
    "updated_at": "2025-03-16T20:52:49.453005",
    "current_progress": 0.0,
    "priority_score": 70.0,
    "additional_funding_sources": "",
    "goal_success_probability": 0.0,
    "adjustments_required": 0,
    "funding_strategy": "",
    "last_simulation_time": null,
    "simulation_data": null,
    "scenarios": null,
    "adjustments": null,
    "simulation_parameters_json": null
  },
  {
    "id": "37589646-c586-414d-94d9-02ef619be320",
    "user_profile_id": "2494fcef-3993-484b-8a21-ca5d057df9cc",
    "category": "home_purchase",
    "title": "Home Purchase",
    "target_amount": 30000000.0,
    "timeframe": "5-10 years",
    "current_amount": 0.0,
    "importance": "high",
    "flexibility": "very_flexible",
    "notes": "Saving for home purchase or down payment",
    "created_at": "2025-03-16T21:01:39.779135",
    "updated_at": "2025-03-16T21:01:41.566816",
    "current_progress": 0.0,
    "priority_score": 75.0,
    "additional_funding_sources": "",
    "goal_success_probability": 0.0,
    "adjustments_required": 0,
    "funding_strategy": "",
    "last_simulation_time": null,
    "simulation_data": null,
    "scenarios": null,
    "adjustments": null,
    "simulation_parameters_json": null
  },
  {
    "id": "6e75a2a2-d863-445a-bdb9-b146bd1b1d2d",
    "user_profile_id": "1cd8e6fd-0713-4f4b-bd16-c181a5dfb0dd",
    "category": "home_purchase",
    "title": "Home Purchase",
    "target_amount": 20000000.0,
    "timeframe": "3-5 years",
    "current_amount": 0.0,
    "importance": "medium",
    "flexibility": "fixed",
    "notes": "Saving for home purchase or down payment",
    "created_at": "2025-03-16T21:10:30.977400",
    "updated_at": "2025-03-16T21:10:32.699092",
    "current_progress": 0.0,
    "priority_score": 70.0,
    "additional_funding_sources": "",
    "goal_success_probability": 0.0,
    "adjustments_required": 0,
    "funding_strategy": "",
    "last_simulation_time": null,
    "simulation_data": null,
    "scenarios": null,
    "adjustments": null,
    "simulation_parameters_json": null
  },
  {
    "id": "0e383430-42cb-4a98-8918-1b73963ece07",
    "user_profile_id": "3b5ac083-40c6-43eb-8a8d-46e2767c45cb",
    "category": "home_purchase",
    "title": "Home Purchase",
    "target_amount": 30000000.0,
    "timeframe": "3-5 years",
    "current_amount": 0.0,
    "importance": "medium",
    "flexibility": "fixed",
    "notes": "Saving for home purchase or down payment",
    "created_at": "2025-03-16T21:23:31.974843",
    "updated_at": "2025-03-16T21:23:36.564847",
    "current_progress": 0.0,
    "priority_score": 70.0,
    "additional_funding_sources": "",
    "goal_success_probability": 0.0,
    "adjustments_required": 0,
    "funding_strategy": "",
    "last_simulation_time": null,
    "simulation_data": null,
    "scenarios": null,
    "adjustments": null,
    "simulation_parameters_json": null
  },
  {
    "id": "3c2fef5b-fe5d-46b8-82f4-af7e2faf59ce",
    "user_profile_id": "9dbfe3b4-fc9d-4923-b725-86f0606fdba4",
    "category": "home_purchase",
    "title": "Home Purchase",
    "target_amount": 23000000.0,
    "timeframe": "5-10 years",
    "current_amount": 0.0,
    "importance": "medium",
    "flexibility": "fixed",
    "notes": "Saving for home purchase or down payment",
    "created_at": "2025-03-16T21:36:30.733357",
    "updated_at": "2025-03-16T21:36:33.207713",
    "current_progress": 0.0,
    "priority_score": 70.0,
    "additional_funding_sources": "",
    "goal_success_probability": 0.0,
    "adjustments_required": 0,
    "funding_strategy": "",
    "last_simulation_time": null,
    "simulation_data": null,
    "scenarios": null,
    "adjustments": null,
    "simulation_parameters_json": null
  },
  {
    "id": "6abda51e-86de-4593-8c48-45eb6b16eb00",
    "user_profile_id": "ac80a648-481a-42dc-bba0-97e63c09d158",
    "category": "home_purchase",
    "title": "Home Purchase",
    "target_amount": 23000000.0,
    "timeframe": "3-5 years",
    "current_amount": 0.0,
    "importance": "medium",
    "flexibility": "fixed",
    "notes": "Saving for home purchase or down payment",
    "created_at": "2025-03-16T21:47:23.361318",
    "updated_at": "2025-03-16T21:47:27.899174",
    "current_progress": 0.0,
    "priority_score": 70.0,
    "additional_funding_sources": "",
    "goal_success_probability": 0.0,
    "adjustments_required": 0,
    "funding_strategy": "",
    "last_simulation_time": null,
    "simulation_data": null,
    "scenarios": null,
    "adjustments": null,
    "simulation_parameters_json": null
  },
  {
    "id": "baab33da-2131-4474-9ce3-c7affba363a5",
    "user_profile_id": "6c27d059-ff1f-4bd4-a75e-8e64a434cfc5",
    "category": "home_purchase",
    "title": "Home Purchase",
    "target_amount": 23000000.0,
    "timeframe": "5-10 years",
    "current_amount": 0.0,
    "importance": "medium",
    "flexibility": "fixed",
    "notes": "Saving for home purchase or down payment",
    "created_at": "2025-03-16T22:17:09.470067",
    "updated_at": "2025-03-16T22:17:12.325736",
    "current_progress": 0.0,
    "priority_score": 70.0,
    "additional_funding_sources": "",
    "goal_success_probability": 0.0,
    "adjustments_required": 0,
    "funding_strategy": "",
    "last_simulation_time": null,
    "simulation_data": null,
    "scenarios": null,
    "adjustments": null,
    "simulation_parameters_json": null
  },
  {
    "id": "f6b875e4-9131-4dba-88aa-dfec319a3cf5",
    "user_profile_id": "1157bd5e-cca0-4f0c-bfb2-a92241f34eeb",
    "category": "home_purchase",
    "title": "Home Purchase",
    "target_amount": 23000000.0,
    "timeframe": "3-5 years",
    "current_amount": 0.0,
    "importance": "medium",
    "flexibility": "fixed",
    "notes": "Saving for home purchase or down payment",
    "created_at": "2025-03-16T22:24:18.953085",
    "updated_at": "2025-03-16T22:24:21.092668",
    "current_progress": 0.0,
    "priority_score": 70.0,
    "additional_funding_sources": "",
    "goal_success_probability": 0.0,
    "adjustments_required": 0,
    "funding_strategy": "",
    "last_simulation_time": null,
    "simulation_data": null,
    "scenarios": null,
    "adjustments": null,
    "simulation_parameters_json": null
  },
  {
    "id": "91caaf86-0716-48b4-9a07-1b7086d76e98",
    "user_profile_id": "c282f8b5-cc1b-4969-ad89-0cf86e55cbc3",
    "category": "home_purchase",
    "title": "Home Purchase",
    "target_amount": 23000000.0,
    "timeframe": "5-10 years",
    "current_amount": 0.0,
    "importance": "medium",
    "flexibility": "fixed",
    "notes": "Saving for home purchase or down payment",
    "created_at": "2025-03-16T22:29:50.501843",
    "updated_at": "2025-03-16T22:29:52.506806",
    "current_progress": 0.0,
    "priority_score": 70.0,
    "additional_funding_sources": "",
    "goal_success_probability": 0.0,
    "adjustments_required": 0,
    "funding_strategy": "",
    "last_simulation_time": null,
    "simulation_data": null,
    "scenarios": null,
    "adjustments": null,
    "simulation_parameters_json": null
  },
  {
    "id": "ae3ccaab-aee9-437b-9460-5994a1e9ab9e",
    "user_profile_id": "7f7ff8b5-8324-4b97-8c03-c2235898554e",
    "category": "home_purchase",
    "title": "Home Purchase",
    "target_amount": 23000000.0,
    "timeframe": "5-10 years",
    "current_amount": 0.0,
    "importance": "medium",
    "flexibility": "fixed",
    "notes": "Saving for home purchase or down payment",
    "created_at": "2025-03-16T22:46:09.877855",
    "updated_at": "2025-03-16T22:46:11.981846",
    "current_progress": 0.0,
    "priority_score": 70.0,
    "additional_funding_sources": "",
    "goal_success_probability": 0.0,
    "adjustments_required": 0,
    "funding_strategy": "",
    "last_simulation_time": null,
    "simulation_data": null,
    "scenarios": null,
    "adjustments": null,
    "simulation_parameters_json": null
  },
  {
    "id": "13564d45-9be2-43b7-ac2c-861ae46ce3bb",
    "user_profile_id": "8a1d08f2-8dd5-4bd4-8c65-a047896dc13c",
    "category": "home_purchase",
    "title": "Home Purchase",
    "target_amount": 32000000.0,
    "timeframe": "3-5 years",
    "current_amount": 0.0,
    "importance": "medium",
    "flexibility": "fixed",
    "notes": "Saving for home purchase or down payment",
    "created_at": "2025-03-16T22:59:38.942117",
    "updated_at": "2025-03-16T22:59:40.793843",
    "current_progress": 0.0,
    "priority_score": 70.0,
    "additional_funding_sources": "",
    "goal_success_probability": 0.0,
    "adjustments_required": 0,
    "funding_strategy": "",
    "last_simulation_time": null,
    "simulation_data": null,
    "scenarios": null,
    "adjustments": null,
    "simulation_parameters_json": null
  },
  {
    "id": "73b9caed-b03c-4030-95a7-970c7cd70993",
    "user_profile_id": "bb84352f-d7a5-4541-88ae-954d2127a7bf",
    "category": "home_purchase",
    "title": "Home Purchase",
    "target_amount": 23000000.0,
    "timeframe": "3-5 years",
    "current_amount": 0.0,
    "importance": "medium",
    "flexibility": "fixed",
    "notes": "Saving for home purchase or down payment",
    "created_at": "2025-03-17T17:21:20.175505",
    "updated_at": "2025-03-17T17:21:22.080180",
    "current_progress": 0.0,
    "priority_score": 70.0,
    "additional_funding_sources": "",
    "goal_success_probability": 0.0,
    "adjustments_required": 0,
    "funding_strategy": "",
    "last_simulation_time": null,
    "simulation_data": null,
    "scenarios": null,
    "adjustments": null,
    "simulation_parameters_json": null
  },
  {
    "id": "2e6715be-945a-46c8-a6df-71307bacda98",
    "user_profile_id": "40eb7a46-d817-45bc-a871-1b216f74d8e8",
    "category": "custom",
    "title": "Car!",
    "target_amount": 350000.0,
    "timeframe": "1-3 years",
    "current_amount": 0.0,
    "importance": "medium",
    "flexibility": "fixed",
    "notes": "Custom goal: Car!",
    "created_at": "2025-03-17T17:49:55.852365",
    "updated_at": "2025-03-17T17:49:57.891881",
    "current_progress": 0.0,
    "priority_score": 70.0,
    "additional_funding_sources": "",
    "goal_success_probability": 0.0,
    "adjustments_required": 0,
    "funding_strategy": "",
    "last_simulation_time": null,
    "simulation_data": null,
    "scenarios": null,
    "adjustments": null,
    "simulation_parameters_json": null
  },
  {
    "id": "a17f0276-c07d-498d-91cc-c8d4b8d2e89b",
    "user_profile_id": "e01f1031-af8b-485a-a875-f0f85029f87a",
    "category": "custom",
    "title": "car",
    "target_amount": 350000.0,
    "timeframe": "1-3 years",
    "current_amount": 0.0,
    "importance": "medium",
    "flexibility": "fixed",
    "notes": "Custom goal: car",
    "created_at": "2025-03-17T18:08:49.326683",
    "updated_at": "2025-03-17T18:08:51.451092",
    "current_progress": 0.0,
    "priority_score": 70.0,
    "additional_funding_sources": "",
    "goal_success_probability": 0.0,
    "adjustments_required": 0,
    "funding_strategy": "",
    "last_simulation_time": null,
    "simulation_data": null,
    "scenarios": null,
    "adjustments": null,
    "simulation_parameters_json": null
  },
  {
    "id": "41a4d986-67da-4d87-b861-dfa46c210cb0",
    "user_profile_id": "d73d6dfd-df95-4349-8c84-d6cfc23bf84a",
    "category": "home_purchase",
    "title": "Home Purchase",
    "target_amount": 23000000.0,
    "timeframe": "3-5 years",
    "current_amount": 0.0,
    "importance": "medium",
    "flexibility": "fixed",
    "notes": "Saving for home purchase or down payment",
    "created_at": "2025-03-17T18:13:45.094496",
    "updated_at": "2025-03-17T18:13:47.585419",
    "current_progress": 0.0,
    "priority_score": 70.0,
    "additional_funding_sources": "",
    "goal_success_probability": 0.0,
    "adjustments_required": 0,
    "funding_strategy": "",
    "last_simulation_time": null,
    "simulation_data": null,
    "scenarios": null,
    "adjustments": null,
    "simulation_parameters_json": null
  },
  {
    "id": "ff35ace3-14fe-4d66-a21d-f00106a3d27f",
    "user_profile_id": "3ba09905-b8e7-40e5-b433-24e9b61aad84",
    "category": "home_purchase",
    "title": "Home Purchase",
    "target_amount": 23000000.0,
    "timeframe": "3-5 years",
    "current_amount": 0.0,
    "importance": "medium",
    "flexibility": "fixed",
    "notes": "Saving for home purchase or down payment",
    "created_at": "2025-03-17T18:24:50.851590",
    "updated_at": "2025-03-17T18:24:52.723766",
    "current_progress": 0.0,
    "priority_score": 70.0,
    "additional_funding_sources": "",
    "goal_success_probability": 0.0,
    "adjustments_required": 0,
    "funding_strategy": "",
    "last_simulation_time": null,
    "simulation_data": null,
    "scenarios": null,
    "adjustments": null,
    "simulation_parameters_json": null
  },
  {
    "id": "439c5af4-d316-425a-b90e-32a633b50b1c",
    "user_profile_id": "2b8de098-832f-446c-8432-e0850012cc57",
    "category": "home_purchase",
    "title": "Home Purchase",
    "target_amount": 23000000.0,
    "timeframe": "5-10 years",
    "current_amount": 0.0,
    "importance": "medium",
    "flexibility": "fixed",
    "notes": "Saving for home purchase or down payment",
    "created_at": "2025-03-18T17:32:35.674811",
    "updated_at": "2025-03-18T17:32:37.798297",
    "current_progress": 0.0,
    "priority_score": 70.0,
    "additional_funding_sources": "",
    "goal_success_probability": 0.0,
    "adjustments_required": 0,
    "funding_strategy": "",
    "last_simulation_time": null,
    "simulation_data": null,
    "scenarios": null,
    "adjustments": null,
    "simulation_parameters_json": null
  },
  {
    "id": "5c661d3e-b25f-4832-baf1-aa3b0ff1ef02",
    "user_profile_id": "8c7d7ae6-e727-4006-8ba8-6a0c262d8114",
    "category": "home_purchase",
    "title": "Home Purchase",
    "target_amount": 23000000.0,
    "timeframe": "5-10 years",
    "current_amount": 0.0,
    "importance": "medium",
    "flexibility": "fixed",
    "notes": "Saving for home purchase or down payment",
    "created_at": "2025-03-18T21:30:32.993152",
    "updated_at": "2025-03-18T21:30:35.112014",
    "current_progress": 0.0,
    "priority_score": 70.0,
    "additional_funding_sources": "",
    "goal_success_probability": 0.0,
    "adjustments_required": 0,
    "funding_strategy": "",
    "last_simulation_time": null,
    "simulation_data": null,
    "scenarios": null,
    "adjustments": null,
    "simulation_parameters_json": null
  },
  {
    "id": "21ed4c3d-03d7-448c-b81f-1c727852b217",
    "user_profile_id": "7f80d26c-13dc-4be5-b599-26b7b07a4a4f",
    "category": "home_purchase",
    "title": "Home Purchase",
    "target_amount": 23000000.0,
    "timeframe": "5-10 years",
    "current_amount": 0.0,
    "importance": "medium",
    "flexibility": "fixed",
    "notes": "Saving for home purchase or down payment",
    "created_at": "2025-03-18T23:09:15.408654",
    "updated_at": "2025-03-18T23:09:42.500059",
    "current_progress": 0.0,
    "priority_score": 70.0,
    "additional_funding_sources": "",
    "goal_success_probability": 0.0,
    "adjustments_required": 0,
    "funding_strategy": "",
    "last_simulation_time": null,
    "simulation_data": null,
    "scenarios": null,
    "adjustments": null,
    "simulation_parameters_json": null
  },
  {
    "id": "32a78fee-ca15-46db-bcd3-d758a8d7fb45",
    "user_profile_id": "7f80d26c-13dc-4be5-b599-26b7b07a4a4f",
    "category": "education",
    "title": "Education Funding",
    "target_amount": 800000.0,
    "timeframe": "3-5 years",
    "current_amount": 0.0,
    "importance": "medium",
    "flexibility": "fixed",
    "notes": "Saving for education expenses",
    "created_at": "2025-03-18T23:09:36.172582",
    "updated_at": "2025-03-18T23:09:42.497193",
    "current_progress": 0.0,
    "priority_score": 70.0,
    "additional_funding_sources": "",
    "goal_success_probability": 0.0,
    "adjustments_required": 0,
    "funding_strategy": "",
    "last_simulation_time": null,
    "simulation_data": null,
    "scenarios": null,
    "adjustments": null,
    "simulation_parameters_json": null
  },
  {
    "id": "119f9c20-8102-4961-9800-14c2090b26f4",
    "user_profile_id": "ad2a56f1-3ecf-4eb7-8351-c5ffabe5416b",
    "category": "home_purchase",
    "title": "Home Purchase",
    "target_amount": 4600000.0,
    "timeframe": "5-10 years",
    "current_amount": 0.0,
    "importance": "medium",
    "flexibility": "fixed",
    "notes": "Saving for home purchase or down payment",
    "created_at": "2025-03-19T18:00:56.744749",
    "updated_at": "2025-03-19T18:01:07.186947",
    "current_progress": 0.0,
    "priority_score": 65.0,
    "additional_funding_sources": "",
    "goal_success_probability": 0.0,
    "adjustments_required": 0,
    "funding_strategy": "",
    "last_simulation_time": null,
    "simulation_data": null,
    "scenarios": null,
    "adjustments": null,
    "simulation_parameters_json": null
  },
  {
    "id": "d8a09510-f946-4959-8d18-0c13655cbe10",
    "user_profile_id": "ad2a56f1-3ecf-4eb7-8351-c5ffabe5416b",
    "category": "education",
    "title": "Education Funding",
    "target_amount": 800000.0,
    "timeframe": "1-3 years",
    "current_amount": 0.0,
    "importance": "medium",
    "flexibility": "fixed",
    "notes": "Saving for education expenses",
    "created_at": "2025-03-19T18:01:05.162087",
    "updated_at": "2025-03-19T18:01:07.183409",
    "current_progress": 0.0,
    "priority_score": 65.0,
    "additional_funding_sources": "",
    "goal_success_probability": 0.0,
    "adjustments_required": 0,
    "funding_strategy": "",
    "last_simulation_time": null,
    "simulation_data": null,
    "scenarios": null,
    "adjustments": null,
    "simulation_parameters_json": null
  },
  {
    "id": "7cc976a7-a599-433d-bfff-13caa6d22fc6",
    "user_profile_id": "a69f742d-7f28-4c3d-87e1-306d030fc74f",
    "category": "emergency_fund",
    "title": "Emergency Fund",
    "target_amount": 360000.0,
    "timeframe": "2025-09-17T12:41:55.512685",
    "current_amount": 100000.0,
    "importance": "high",
    "flexibility": "fixed",
    "notes": "Build emergency fund for unexpected expenses",
    "created_at": "2025-03-21T12:41:55.512704",
    "updated_at": "2025-03-21T12:41:55.514033",
    "current_progress": 27.77777777777778,
    "priority_score": 92.87,
    "additional_funding_sources": "",
    "goal_success_probability": 57.5,
    "adjustments_required": 0,
    "funding_strategy": "{\"strategy\": \"monthly_contribution\", \"amount\": 50644.60679481713, \"months\": 6}",
    "last_simulation_time": null,
    "simulation_data": null,
    "scenarios": null,
    "adjustments": null,
    "simulation_parameters_json": null
  },
  {
    "id": "c691560e-f59d-408d-b6e8-ffbd9c61fb64",
    "user_profile_id": "f225e431-7f08-49f5-8c0b-b949518a89c1",
    "category": "traditional_retirement",
    "title": "Retirement Corpus",
    "target_amount": 77253672.9553828,
    "timeframe": "2050-03-15T12:41:55.516484",
    "current_amount": 2000000.0,
    "importance": "high",
    "flexibility": "somewhat_flexible",
    "notes": "Build retirement corpus for comfortable retirement at age 60",
    "created_at": "2025-03-21T12:41:55.516499",
    "updated_at": "2025-03-21T12:41:55.517777",
    "current_progress": 2.5888736722655024,
    "priority_score": 61.26,
    "additional_funding_sources": "",
    "goal_success_probability": 61.5533242033593,
    "adjustments_required": 0,
    "funding_strategy": "{\"strategy\": \"monthly_contribution\", \"amount\": 66406.93971816772, \"retirement_age\": 60}",
    "last_simulation_time": null,
    "simulation_data": null,
    "scenarios": null,
    "adjustments": null,
    "simulation_parameters_json": null
  },
  {
    "id": "29da6424-974a-4773-a3b5-90e45f37de76",
    "user_profile_id": "52f0a841-7d60-4549-9105-68471cd1ad47",
    "category": "emergency_fund",
    "title": "Emergency Fund",
    "target_amount": 360000.0,
    "timeframe": "2025-09-17T12:42:49.583477",
    "current_amount": 100000.0,
    "importance": "high",
    "flexibility": "fixed",
    "notes": "Build emergency fund for unexpected expenses",
    "created_at": "2025-03-21T12:42:49.583507",
    "updated_at": "2025-03-21T12:42:49.585136",
    "current_progress": 27.77777777777778,
    "priority_score": 92.87,
    "additional_funding_sources": "",
    "goal_success_probability": 57.5,
    "adjustments_required": 0,
    "funding_strategy": "{\"strategy\": \"monthly_contribution\", \"amount\": 50644.60679481713, \"months\": 6}",
    "last_simulation_time": null,
    "simulation_data": null,
    "scenarios": null,
    "adjustments": null,
    "simulation_parameters_json": null
  },
  {
    "id": "53c57048-86c0-49c4-a0f3-3af55dc02d62",
    "user_profile_id": "a70ef940-a157-4233-b4cc-5476aa689a71",
    "category": "traditional_retirement",
    "title": "Retirement Corpus",
    "target_amount": 77253672.9553828,
    "timeframe": "2050-03-15T12:42:49.588191",
    "current_amount": 2000000.0,
    "importance": "high",
    "flexibility": "somewhat_flexible",
    "notes": "Build retirement corpus for comfortable retirement at age 60",
    "created_at": "2025-03-21T12:42:49.588218",
    "updated_at": "2025-03-21T12:42:49.589610",
    "current_progress": 2.5888736722655024,
    "priority_score": 61.26,
    "additional_funding_sources": "",
    "goal_success_probability": 61.5533242033593,
    "adjustments_required": 0,
    "funding_strategy": "{\"strategy\": \"monthly_contribution\", \"amount\": 66406.93971816772, \"retirement_age\": 60}",
    "last_simulation_time": null,
    "simulation_data": null,
    "scenarios": null,
    "adjustments": null,
    "simulation_parameters_json": null
  },
  {
    "id": "e7ffc844-d828-40b0-9976-24469eb989c9",
    "user_profile_id": "84f6e1e8-b314-4902-b186-97edee9796be",
    "category": "emergency_fund",
    "title": "Emergency Fund",
    "target_amount": 360000.0,
    "timeframe": "2025-09-17T12:43:40.379715",
    "current_amount": 100000.0,
    "importance": "high",
    "flexibility": "fixed",
    "notes": "Build emergency fund for unexpected expenses",
    "created_at": "2025-03-21T12:43:40.379732",
    "updated_at": "2025-03-21T12:43:40.381043",
    "current_progress": 27.77777777777778,
    "priority_score": 92.87,
    "additional_funding_sources": "",
    "goal_success_probability": 57.5,
    "adjustments_required": 0,
    "funding_strategy": "{\"strategy\": \"monthly_contribution\", \"amount\": 50644.60679481713, \"months\": 6}",
    "last_simulation_time": null,
    "simulation_data": null,
    "scenarios": null,
    "adjustments": null,
    "simulation_parameters_json": null
  },
  {
    "id": "78bbca7d-cdd9-40de-8b2e-db91644fcae7",
    "user_profile_id": "256f43f9-5fc7-40a0-bdf0-dcf5ef71da0a",
    "category": "traditional_retirement",
    "title": "Retirement Corpus",
    "target_amount": 77253672.9553828,
    "timeframe": "2050-03-15T12:43:40.383325",
    "current_amount": 2000000.0,
    "importance": "high",
    "flexibility": "somewhat_flexible",
    "notes": "Build retirement corpus for comfortable retirement at age 60",
    "created_at": "2025-03-21T12:43:40.383341",
    "updated_at": "2025-03-21T12:43:40.384424",
    "current_progress": 2.5888736722655024,
    "priority_score": 61.26,
    "additional_funding_sources": "",
    "goal_success_probability": 61.5533242033593,
    "adjustments_required": 0,
    "funding_strategy": "{\"strategy\": \"monthly_contribution\", \"amount\": 66406.93971816772, \"retirement_age\": 60}",
    "last_simulation_time": null,
    "simulation_data": null,
    "scenarios": null,
    "adjustments": null,
    "simulation_parameters_json": null
  }
]